<?xml version="1.0" encoding="UTF-8"?>
<krpano>


  <data name="en_project_title"><![CDATA[mahmudi]]></data>



  <data name="en_pano92_title"><![CDATA[hallway]]></data>


  <data name="en_pano38_title"><![CDATA[kitchen]]></data>


  <data name="en_pano36_title"><![CDATA[dining and tv area]]></data>


  <data name="en_pano40_title"><![CDATA[aisle]]></data>


  <data name="en_pano44_title"><![CDATA[master entrance]]></data>


  <data name="en_pano50_title"><![CDATA[masterbathroom]]></data>


  <data name="en_pano83_title"><![CDATA[livingroom]]></data>


  <data name="en_pano87_title"><![CDATA[general service]]></data>


  <data name="en_pano98_title"><![CDATA[boy bedroom]]></data>


  <data name="en_pano105_title"><![CDATA[girl bedroom]]></data>


  <data name="en_pano108_title"><![CDATA[masterbedroom]]></data>









































</krpano>